metaappscriptsdk/__init__.py
metaappscriptsdk/apiclient.py
metaappscriptsdk/exceptions.py
metaappscriptsdk/info.py
metaappscriptsdk/internal.py
metaappscriptsdk/utils.py
metaappscriptsdk/worker.py
metaappscriptsdk/feed/FeedColumn.py
metaappscriptsdk/feed/ParseXml.py
metaappscriptsdk/feed/__init__.py
metaappscriptsdk/logger/__init__.py
metaappscriptsdk/logger/bulk_logger.py
metaappscriptsdk/logger/logger.py
metaappscriptsdk/schedule/Schedule.py
metaappscriptsdk/schedule/__init__.py
metaappscriptsdk/services/ApiProxyService.py
metaappscriptsdk/services/DbQueryService.py
metaappscriptsdk/services/DbService.py
metaappscriptsdk/services/ExportService.py
metaappscriptsdk/services/ExternalSystemService.py
metaappscriptsdk/services/FeedService.py
metaappscriptsdk/services/IssueService.py
metaappscriptsdk/services/MailService.py
metaappscriptsdk/services/MediaService.py
metaappscriptsdk/services/MetaqlService.py
metaappscriptsdk/services/SettingsService.py
metaappscriptsdk/services/StarterService.py
metaappscriptsdk/services/UserManagementService.py
metaappscriptsdk/services/__init__.py
metaappscriptsdk-0.7.0.dist-info/METADATA
metaappscriptsdk-0.7.0.dist-info/RECORD
metaappscriptsdk-0.7.0.dist-info/WHEEL
metaappscriptsdk-0.7.0.dist-info/top_level.txt
