Metadata-Version: 2.1
Name: metaappscriptsdk
Version: 0.7.0
Summary: Meta App Scripts SDK
Home-page: https://github.com/rw-meta/meta-app-script-py-sdk
Author: Artur Geraschenko
Author-email: arturgspb@gmail.com
License: MIT
Platform: UNKNOWN
Classifier: Programming Language :: Python :: 3
Requires-Dist: elasticsearch (==2.3.0)
Requires-Dist: jsonklog (==0.15.0)
Requires-Dist: six (==1.10.0)
Requires-Dist: croniter (==0.3.14)
Requires-Dist: python-logstash (==0.4.6)
Requires-Dist: fluent-logger (==0.9.3)
Requires-Dist: PyJWT (==1.5.3)
